Workbook

Sheet Sheet1
A1: Case Study: Top-Down vs Bottom-Up Budget Comparison
A2: Task: Compare two different budgeting approaches for the same company and identify key differences
A4: Scenario: GrowthTech Inc. - FY2027 Budget
A5: You are the FP&A Analyst at P&P Inc., a mid-sized software company. The CEO wants to achieve $20 M in annual revenue.
A6: Department heads have submitted their bottom-up plans totaling $12.5M in revenue.
A7: Your task is to reconcile these two approaches and provide recommendations.
A9: Top-Down Budget (Leadership Target)
A10: Line Item | B10: FY2027 | C10: % of Revenue | D10: Notes
A11: Revenue Target | B11: 20000000 | D11: CEO Strategic Goal
A12: Gross Profit Target | B12: =B11*C12 -> 15000000 | C12: 0.75 | D12: 75% target margin
A13: S&M Budget | B13: =B11*C13 -> 7000000 | C13: 0.35 | D13: 35% of revenue
A14: R&D Budget | B14: =B11*C14 -> 4000000 | C14: 0.2 | D14: 20% of revenue
A15: G&A Budget | B15: =B11*C15 -> 2000000 | C15: 0.1 | D15: 10% of revenue
A16: Total OpEx | B16: =B13+B14+B15 -> 13000000 | C16: 0.65 | D16: 65% of revenue
A17: Target EBITDA | B17: =B11*C17 -> 2000000 | C17: 0.1 | D17: 10% target margin
A19: Bottom-Up Budget (Department Submissions)
A20: Line Item | B20: FY2027 | C20: % of Revenue | D20: Notes
A21: Revenue Plan | B21: 15000000 | D21: Sales team forecast
A22: Gross Profit | B22: =B21*C22 -> 11250000 | C22: 0.75 | D22: Same margin assumption
A23: S&M Plan | B23: =B21*C23 -> 5550000 | C23: 0.37 | D23: Dept. head request
A24: R&D Plan | B24: =B21*C24 -> 4200000 | C24: 0.28 | D24: Dept. head request
A25: G&A Plan | B25: =B21*C25 -> 2550000 | C25: 0.17 | D25: Dept. head request
A26: Total OpEx | B26: =B23+B24+B25 -> 12300000 | C26: 0.82 | D26: Higher than target
A27: Projected EBITDA | B27: =B21*C27 -> -1050000 | C27: -0.07 | D27: Negative margin
A29: Analyse:
A30: 1. Revenue Gap | D30: Calculate the difference between top-down and bottom-up revenue
A31: 2. OpEx Gap | D31: Calculate the difference in total operating expenses
A32: 3. Key Issues | D32: What are the main conflicts between the two approaches?
A33: 4. Recommendation | D33: Which approach is more realistic? What adjustments are needed?
A34: 5. Next Steps | D34: How would you reconcile these differences?

Sheet Sheet2
A1: Budget Approach Comparison & Reconciliation
A3: Variance Analysis: Top-Down vs Bottom-Up
A4: Metric | B4: Top-Down | C4: Bottom-Up | D4: Variance
A5: Revenue | B5: =B19 -> 20000000 | C5: =C19 -> 15000000 | D5: =C5-B5 -> -5000000
A6: Total OpEx | B6: =B24 -> 13000000 | C6: =C24 -> 12300000 | D6: =C6-B6 -> -700000
A7: EBITDA | B7: =B25 -> 2000000 | C7: =C25 -> -1050000 | D7: =C7-B7 -> -3050000
A8: EBITDA Margin % | B8: =B7/B5 -> 0.1 | C8: =C7/C5 -> -0.07
A10: Key Findings
A11: 1. Revenue gap: Bottom-up forecast is $5M (25%) below top-down target. Sales team may lack confidence or resources to hit CEO goal.
A12: 2. OpEx Overspend: Despite lower revenue, departments requested more in spending. OpEx ratio is 82% vs 65% TARGET.
A13: 3. Profitability crisis: Bottom-up plan shows negative EBITDA of $1050000 vs target of +$2M profit. $9.5M gap.
A14: 4. Department Inefficiency: Each department exceeded their % allocation.
A15: 5. Unrealistic expectations: Top-down target may be too aggressive without corresponding investment in sales capacity.
A17: Recommended Reconciliation Approach
A18: Line Item | B18: Top-Down | C18: Bottom-Up | D18: Recommended | E18: Rationale
A19: Revenue | B19: =Sheet1!B11 -> 20000000 | C19: =Sheet1!B21 -> 15000000 | D19: =C19*1.1 -> 16500000 | E19: Stretch goal: +10% above bottom-up
A20: Gross Profit | B20: =Sheet1!B12 -> 15000000 | C20: =Sheet1!B22 -> 11250000 | D20: =D19*75% -> 12375000 | E20: Maintain 75% margin
A21: S&M (40%) | B21: =Sheet1!B13 -> 7000000 | C21: =Sheet1!B23 -> 5550000 | D21: =D19*40% -> 6600000 | E21: Invest more to hit revenue target
A22: R&D (23%) | B22: =Sheet1!B14 -> 4000000 | C22: =Sheet1!B24 -> 4200000 | D22: =D19*23% -> 3795000 | E22: Compromise between targets
A23: G&A (12%) | B23: =Sheet1!B15 -> 2000000 | C23: =Sheet1!B25 -> 2550000 | D23: =D19*12% -> 1980000 | E23: Trim to 12% from deptt request
A24: Total OpEx | B24: =Sheet1!B16 -> 13000000 | C24: =Sheet1!B26 -> 12300000 | D24: =SUM(D21:D23) -> 12375000 | E24: Match gross profit exactly
A25: EBITDA | B25: =Sheet1!B17 -> 2000000 | C25: =Sheet1!B27 -> -1050000 | D25: =D20-D24 -> 0 | E25: Breakeven year, invest for growth
A27: Implementation Steps & Best Practices
A28: 1.Collaborate with Sales: Push the sales team to commit to a $16.5M target by leveraging higher marketing and sales investments, and hire 3 to 5 additional sales representatives.
A29: 2.Rank R&D Tasks: Delay lower-priority research and development projects to maintain development speed without exceeding the budget.
A30: 3.Conduct Quarterly Audits: Use rolling forecasts to review financial performance every quarter and adjust the budget based on real versus planned outcomes.
A31: 4.Prepare Alternative Scenarios: Design plans for both best-case and worst-case outcomes. Allocate extra revenue to savings if sales hit $20M, but execute cost reductions if targets are missed.
A32: 5.Enforce Responsibility: Link executive bonuses directly to meeting the finalized budget, and hold monthly variance evaluation meetings with department leaders.
A33: 6.Keep Stakeholders Informed: Pitch the reconciled budget to the board as a strategic "Investment Year," framing a break-even result as an acceptable trade-off for scaling the business.
A34: 7.Set Aside Emergency Funds: Establish a 5% contingency reserve for unexpected costs, which can only be utilized with explicit CFO authorization.
A36: Key Learnings from This Exercise
A37: • Top-down budgets ensure strategic alignment but may lack operational realism
A38: • Bottom-up budgets are more accurate but can lead to sandbagging and empire-building
A39: • Successful FP&A professionals bridge the gap through data-driven negotiation
... A44: • Build flexibility with scenarios and rolling forecasts to adapt to changing conditions
